seatre/__init__.py
seatre/arp_spoofing.py
seatre/bpdu.py
seatre/helpers.py
seatre/mac_flood.py
seatre/syn_flood.py
seatre/udp_flood.py
seatre-1.0.0.dist-info/LICENSE
seatre-1.0.0.dist-info/METADATA
seatre-1.0.0.dist-info/WHEEL
seatre-1.0.0.dist-info/RECORD
