Metadata-Version: 2.1
Name: seatre
Version: 1.0.0
Summary: Scripts that implement different network attacks
License: GPL-3.0 license
Author: nadzyah
Author-email: nadzya.info@gmail.com
Requires-Python: >=3.10,<4.0
Classifier: License :: Other/Proprietary License
Classifier: Programming Language :: Python :: 3
Classifier: Programming Language :: Python :: 3.10
Classifier: Programming Language :: Python :: 3.11
Classifier: Programming Language :: Python :: 3.12
Requires-Dist: pylintfileheader (>=1.0.0,<2.0.0)
Requires-Dist: scapy (>=2.5.0,<3.0.0)
Requires-Dist: wikipedia (>=1.4.0,<2.0.0)
